pytopys/__init__.py
pytopys-0.0.1.dist-info/LICENSE.txt
pytopys-0.0.1.dist-info/METADATA
pytopys-0.0.1.dist-info/WHEEL
pytopys-0.0.1.dist-info/top_level.txt
pytopys-0.0.1.dist-info/RECORD
